<?xml version="1.0" encoding="UTF-8" standalone="yes"?>
<AssignMessage continueOnError="false" enabled="true" name="AM-setResponseContentLogs">
    <DisplayName>AM-setResponseContentLogs</DisplayName>
    <Properties/>
    <AssignVariable>
        <Name>responseContentPayload</Name>
        <Ref>response.content</Ref>
    </AssignVariable>
    <IgnoreUnresolvedVariables>true</IgnoreUnresolvedVariables>
    <AssignTo createNew="false" transport="http" type="response">response</AssignTo>
</AssignMessage>