<?xml version="1.0" encoding="UTF-8" standalone="yes"?>
<RaiseFault async="false" continueOnError="false" enabled="true" name="RF-handlePreflightRequest">
    <DisplayName>RF-handlePreflightRequest</DisplayName>
    <Properties/>
    <FaultResponse>
        <Set>
            <Headers/>
            <Payload contentType="text/plain"/>
            <StatusCode>200</StatusCode>
            <ReasonPhrase>OK</ReasonPhrase>
        </Set>
        <AssignVariable>
            <Name>apigw.code</Name>
            <Value>200</Value>
        </AssignVariable>
        <AssignVariable>
            <Name>apigw.message</Name>
            <Value>OK</Value>
        </AssignVariable>
    </FaultResponse>
    <IgnoreUnresolvedVariables>true</IgnoreUnresolvedVariables>
</RaiseFault>